SportScience/__init__.py
SportScience/transform.py
sportscience-0.0.1.dist-info/METADATA
sportscience-0.0.1.dist-info/WHEEL
sportscience-0.0.1.dist-info/RECORD
