Metadata-Version: 2.1
Name: SportScience
Version: 0.0.1
Summary: Sport science package created to help transform sport tech data into a more usable form
License: MIT
Keywords: Sport Science,sport technology
Author: Jose Bimbela
Author-email: josebimbela19@gmail.com
Requires-Python: >=3.9,<4.0
Classifier: License :: OSI Approved :: MIT License
Classifier: Programming Language :: Python :: 3
Classifier: Programming Language :: Python :: 3.9
Classifier: Programming Language :: Python :: 3.10
Classifier: Programming Language :: Python :: 3.11
Classifier: Programming Language :: Python :: 3.12
Requires-Dist: matplotlib (>=3.5.1,<4.0.0)
Requires-Dist: numpy (>=1.21.2,<2.0.0)
Requires-Dist: pandas (>=1.3.3,<2.0.0)
Requires-Dist: seaborn (>=0.11.2,<0.12.0)
